enum/LICENSE
enum/README
enum/__init__.py
enum34-1.1.9.dist-info/METADATA
enum34-1.1.9.dist-info/RECORD
enum34-1.1.9.dist-info/WHEEL
enum34-1.1.9.dist-info/top_level.txt
