Metadata-Version: 1.1
Name: enum34
Version: 1.1.9
Summary: Python 3.4 Enum backported to 3.3, 3.2, 3.1, 2.7, 2.6, 2.5, and 2.4
Home-page: https://bitbucket.org/stoneleaf/enum34
Author: Ethan Furman
Author-email: ethan@stoneleaf.us
License: BSD License
Platform: UNKNOWN
Classifier: Development Status :: 5 - Production/Stable
Classifier: Intended Audience :: Developers
Classifier: License :: OSI Approved :: BSD License
Classifier: Programming Language :: Python
Classifier: Topic :: Software Development
Classifier: Programming Language :: Python :: 2.4
Classifier: Programming Language :: Python :: 2.5
Classifier: Programming Language :: Python :: 2.6
Classifier: Programming Language :: Python :: 2.7
Classifier: Programming Language :: Python :: 3.3
Provides: enum
